Metadata-Version: 2.1
Name: cloudindex
Version: 0.0.6
Summary: Cloud bucket indexer
Home-page: https://github.com/divi255/cloud-index
Author: Sergei S.
Author-email: s@makeitwork.cz
License: MIT
Platform: UNKNOWN
Classifier: Programming Language :: Python :: 3
Classifier: License :: OSI Approved :: MIT License
Classifier: Topic :: Internet
Classifier: Topic :: Utilities
